adk/__init__.py
adk/file.py
adk/main.py
adk/commands/__init__.py
adk/commands/conf.py
adk/commands/helper.py
adk/commands/info.py
adk/commands/init.py
adk/commands/pack.py
adk/commands/version.py
adk/console/__init__.py
adk/console/confirm.py
adk/console/datatypes.py
adk/console/message.py
adk/console/out.py
adk/console/query.py
adk/errs/__init__.py
adk/errs/main.py
adk/glovars/__init__.py
adk/glovars/inited.py
atmsg_adk-0.0.0.data/scripts/adk
atmsg_adk-0.0.0.dist-info/LICENSE
atmsg_adk-0.0.0.dist-info/METADATA
atmsg_adk-0.0.0.dist-info/WHEEL
atmsg_adk-0.0.0.dist-info/top_level.txt
atmsg_adk-0.0.0.dist-info/RECORD
